{
    "0": {
        "Bookid": 1,
        "Question": "",
        "Type": 2,
        "Options": [
            "",
            "",
            "",
            ""
        ],
        "Ans": "",
        "Category": ""
    },
    "1": {
        "Bookid": 142,
        "Question": "《苏菲的世界》是挪威作家乔斯坦·贾德创作的一本关于西方哲学史的长篇小说。",
        "Type": 1,
        "Options": [
            "true",
            "false"
        ],
        "Ans": "true",
        "Category": "writer"
    },
    "2": {
        "Bookid": 142,
        "Question": "《苏菲的世界》以小说的形式，通过一名哲学导师向一个叫苏菲的女孩传授哲学知识的经过，揭示了西方哲学史发展的历程。",
        "Type": 1,
        "Options": [
            "true",
            "false"
        ],
        "Ans": "true",
        "Category": "content"
    },
    "3": {
        "Bookid": 142,
        "Question": "《苏菲的世界》被誉为20世纪百部经典著作之一。",
        "Type": 1,
        "Options": [
            "true",
            "false"
        ],
        "Ans": "true",
        "Category": "anecdote"
    },
    "4": {
        "Bookid": 142,
        "Question": "在《苏菲的世界》中，14岁的少女苏菲某天放学回家，收到了神秘的一封信——“你是谁？世界从哪里来？”与此同时，她收到一封古怪的明信片，上面的收件人是“请苏菲转交给席德（Hilde）”，邮戳来自黎巴嫩。",
        "Type": 1,
        "Options": [
            "true",
            "false"
        ],
        "Ans": "true",
        "Category": "figure"
    },
    "5": {
        "Bookid": 142,
        "Question": "在《苏菲的世界》中，在一位神秘导师艾伯特的指引下，苏菲开始思索从古希腊到康德，从祁克果到弗洛伊德等各位大师所思考的根本问题。",
        "Type": 1,
        "Options": [
            "true",
            "false"
        ],
        "Ans": "true",
        "Category": "figure"
    }
}