{
    "0": {
        "Bookid": 1,
        "Question": "",
        "Type": 2,
        "Options": [
            "",
            "",
            "",
            ""
        ],
        "Ans": "",
        "Category": ""
    },
    "1": {
        "Bookid": 68,
        "Question": "《诗经》是中国汉族文学上最早的一部诗歌总集,它又称（ ）",
        "Type": 2,
        "Options": [
            "《民歌》",
            "《诗歌》",
            "《诗》",
            "《诗两百》"
        ],
        "Ans": "《诗》",
        "Category": "anecdote"
    },
    "2": {
        "Bookid": 68,
        "Question": "《诗经》中描写地方民间风俗的是那一部分（ ）",
        "Type": 2,
        "Options": [
            "风",
            "颂",
            "小雅",
            "大雅"
        ],
        "Ans": "风",
        "Category": "content"
    },
    "3": {
        "Bookid": 68,
        "Question": "《诗经》中主要是宗庙乐歌的是哪一部分（ ）",
        "Type": 2,
        "Options": [
            "风",
            "颂",
            "小雅",
            "大雅"
        ],
        "Ans": "颂",
        "Category": "content"
    },
    "4": {
        "Bookid": 68,
        "Question": "《诗经》全书收录了自( )至春秋中叶的作品",
        "Type": 2,
        "Options": [
            "夏朝",
            "商朝",
            "西周初年",
            "东周初年"
        ],
        "Ans": "西周初年",
        "Category": "content"
    },
    "5": {
        "Bookid": 68,
        "Question": "《诗经》的主要采集者并尊称为“中华诗祖”的是（ ）",
        "Type": 2,
        "Options": [
            "王夫子",
            "姜子牙",
            "庄子",
            "尹吉甫"
        ],
        "Ans": "尹吉甫",
        "Category": "writer"
    }
}